setup.py
BrickPython/BrickPi.py
BrickPython/BrickPiWrapper.py
BrickPython/CommandLineApplication.py
BrickPython/Motor.py
BrickPython/Scheduler.py
BrickPython/Sensor.py
BrickPython/TkApplication.py
BrickPython/__init__.py
BrickPython.egg-info/PKG-INFO
BrickPython.egg-info/SOURCES.txt
BrickPython.egg-info/dependency_links.txt
BrickPython.egg-info/not-zip-safe
BrickPython.egg-info/requires.txt
BrickPython.egg-info/top_level.txt
ExamplePrograms/DoorControl.py
ExamplePrograms/MotorController.py
ExamplePrograms/SimpleApp.py
ExamplePrograms/TrialApp.py
ExamplePrograms/__init__.py
test/TestBrickPiWrapper.py
test/TestMotor.py
test/TestScheduler.py
test/TestSensor.py
test/__init__.py