Metadata-Version: 1.0
Name: BrickPython
Version: 0.4
Summary: Python interface for the BrickPi using Objects and Coroutines
Home-page: https://github.com/charlesweir/BrickPython
Author: Charles Weir
Author-email: charles@penrillian.com
License: MIT License
Platform: any
Classifier: Programming Language :: Python
Classifier: Development Status :: 4 - Beta
Classifier: Natural Language :: English
Classifier: Intended Audience :: Developers
Classifier: License :: OSI Approved :: MIT License
Classifier: Operating System :: OS Independent
Classifier: Topic :: Software Development :: Libraries :: Python Modules
Classifier: Topic :: Software Development :: Libraries :: Application Frameworks
